{
  "company": "Aon",
  "questions": [
    {
      "id": 3053,
      "title": "Classifying Triangles by Lengths",
      "difficulty": "Easy",
      "acceptance": "51.3%",
      "frequency": "87.5%",
      "leetcodeUrl": "https://leetcode.com/problems/classifying-triangles-by-lengths"
    },
    {
      "id": 3022,
      "title": "Minimize OR of Remaining Elements Using Operations",
      "difficulty": "Hard",
      "acceptance": "30.3%",
      "frequency": "87.5%",
      "leetcodeUrl": "https://leetcode.com/problems/minimize-or-of-remaining-elements-using-operations"
    },
    {
      "id": 3315,
      "title": "Construct the Minimum Bitwise Array II",
      "difficulty": "Medium",
      "acceptance": "66.6%",
      "frequency": "100.0%",
      "leetcodeUrl": "https://leetcode.com/problems/construct-the-minimum-bitwise-array-ii"
    },
    {
      "id": 3314,
      "title": "Construct the Minimum Bitwise Array I",
      "difficulty": "Easy",
      "acceptance": "85.2%",
      "frequency": "100.0%",
      "leetcodeUrl": "https://leetcode.com/problems/construct-the-minimum-bitwise-array-i"
    },
    {
      "id": 200,
      "title": "Number of Islands",
      "difficulty": "Medium",
      "acceptance": "64.4%",
      "frequency": "62.5%",
      "leetcodeUrl": "https://leetcode.com/problems/number-of-islands"
    }
  ]
}