{
  "company": "Cvent",
  "questions": [
    {
      "id": 138,
      "title": "Copy List with Random Pointer",
      "difficulty": "Medium",
      "acceptance": "62.9%",
      "frequency": "100.0%",
      "leetcodeUrl": "https://leetcode.com/problems/copy-list-with-random-pointer"
    },
    {
      "id": 179,
      "title": "Largest Number",
      "difficulty": "Medium",
      "acceptance": "43.1%",
      "frequency": "100.0%",
      "leetcodeUrl": "https://leetcode.com/problems/largest-number"
    }
  ]
}