{
  "company": "Ibm",
  "questions": [
    {
      "id": 1,
      "title": "Two Sum",
      "difficulty": "Easy",
      "acceptance": "57.5%",
      "frequency": "87.5%",
      "leetcodeUrl": "https://leetcode.com/problems/two-sum"
    },
    {
      "id": 3,
      "title": "Longest Substring Without Repeating Characters",
      "difficulty": "Medium",
      "acceptance": "39.1%",
      "frequency": "87.5%",
      "leetcodeUrl": "https://leetcode.com/problems/longest-substring-without-repeating-characters"
    },
    {
      "id": 4,
      "title": "Median of Two Sorted Arrays",
      "difficulty": "Hard",
      "acceptance": "46.6%",
      "frequency": "37.5%",
      "leetcodeUrl": "https://leetcode.com/problems/median-of-two-sorted-arrays"
    },
    {
      "id": 5,
      "title": "Longest Palindromic Substring",
      "difficulty": "Medium",
      "acceptance": "37.8%",
      "frequency": "62.5%",
      "leetcodeUrl": "https://leetcode.com/problems/longest-palindromic-substring"
    },
    {
      "id": 9,
      "title": "Palindrome Number",
      "difficulty": "Easy",
      "acceptance": "60.6%",
      "frequency": "62.5%",
      "leetcodeUrl": "https://leetcode.com/problems/palindrome-number"
    },
    {
      "id": 12,
      "title": "Integer to Roman",
      "difficulty": "Medium",
      "acceptance": "71.0%",
      "frequency": "87.5%",
      "leetcodeUrl": "https://leetcode.com/problems/integer-to-roman"
    },
    {
      "id": 13,
      "title": "Roman to Integer",
      "difficulty": "Easy",
      "acceptance": "66.6%",
      "frequency": "75.0%",
      "leetcodeUrl": "https://leetcode.com/problems/roman-to-integer"
    },
    {
      "id": 14,
      "title": "Longest Common Prefix",
      "difficulty": "Easy",
      "acceptance": "47.6%",
      "frequency": "50.0%",
      "leetcodeUrl": "https://leetcode.com/problems/longest-common-prefix"
    },
    {
      "id": 17,
      "title": "Letter Combinations of a Phone Number",
      "difficulty": "Medium",
      "acceptance": "66.1%",
      "frequency": "62.5%",
      "leetcodeUrl": "https://leetcode.com/problems/letter-combinations-of-a-phone-number"
    },
    {
      "id": 20,
      "title": "Valid Parentheses",
      "difficulty": "Easy",
      "acceptance": "44.2%",
      "frequency": "75.0%",
      "leetcodeUrl": "https://leetcode.com/problems/valid-parentheses"
    },
    {
      "id": 48,
      "title": "Rotate Image",
      "difficulty": "Medium",
      "acceptance": "80.1%",
      "frequency": "75.0%",
      "leetcodeUrl": "https://leetcode.com/problems/rotate-image"
    },
    {
      "id": 49,
      "title": "Group Anagrams",
      "difficulty": "Medium",
      "acceptance": "72.6%",
      "frequency": "62.5%",
      "leetcodeUrl": "https://leetcode.com/problems/group-anagrams"
    },
    {
      "id": 53,
      "title": "Maximum Subarray",
      "difficulty": "Medium",
      "acceptance": "53.3%",
      "frequency": "50.0%",
      "leetcodeUrl": "https://leetcode.com/problems/maximum-subarray"
    },
    {
      "id": 2904,
      "title": "Shortest and Lexicographically Smallest Beautiful String",
      "difficulty": "Medium",
      "acceptance": "41.1%",
      "frequency": "37.5%",
      "leetcodeUrl": "https://leetcode.com/problems/shortest-and-lexicographically-smallest-beautiful-string"
    },
    {
      "id": 88,
      "title": "Merge Sorted Array",
      "difficulty": "Easy",
      "acceptance": "54.9%",
      "frequency": "37.5%",
      "leetcodeUrl": "https://leetcode.com/problems/merge-sorted-array"
    },
    {
      "id": 2907,
      "title": "Maximum Profitable Triplets With Increasing Prices I",
      "difficulty": "Medium",
      "acceptance": "55.9%",
      "frequency": "62.5%",
      "leetcodeUrl": "https://leetcode.com/problems/maximum-profitable-triplets-with-increasing-prices-i"
    },
    {
      "id": 121,
      "title": "Best Time to Buy and Sell Stock",
      "difficulty": "Easy",
      "acceptance": "56.8%",
      "frequency": "87.5%",
      "leetcodeUrl": "https://leetcode.com/problems/best-time-to-buy-and-sell-stock"
    },
    {
      "id": 128,
      "title": "Longest Consecutive Sequence",
      "difficulty": "Medium",
      "acceptance": "47.1%",
      "frequency": "50.0%",
      "leetcodeUrl": "https://leetcode.com/problems/longest-consecutive-sequence"
    },
    {
      "id": 2921,
      "title": "Maximum Profitable Triplets With Increasing Prices II",
      "difficulty": "Hard",
      "acceptance": "46.1%",
      "frequency": "62.5%",
      "leetcodeUrl": "https://leetcode.com/problems/maximum-profitable-triplets-with-increasing-prices-ii"
    },
    {
      "id": 146,
      "title": "LRU Cache",
      "difficulty": "Medium",
      "acceptance": "47.4%",
      "frequency": "50.0%",
      "leetcodeUrl": "https://leetcode.com/problems/lru-cache"
    },
    {
      "id": 169,
      "title": "Majority Element",
      "difficulty": "Easy",
      "acceptance": "66.3%",
      "frequency": "37.5%",
      "leetcodeUrl": "https://leetcode.com/problems/majority-element"
    },
    {
      "id": 2964,
      "title": "Number of Divisible Triplet Sums",
      "difficulty": "Medium",
      "acceptance": "67.6%",
      "frequency": "75.0%",
      "leetcodeUrl": "https://leetcode.com/problems/number-of-divisible-triplet-sums"
    },
    {
      "id": 189,
      "title": "Rotate Array",
      "difficulty": "Medium",
      "acceptance": "44.9%",
      "frequency": "37.5%",
      "leetcodeUrl": "https://leetcode.com/problems/rotate-array"
    },
    {
      "id": 238,
      "title": "Product of Array Except Self",
      "difficulty": "Medium",
      "acceptance": "68.9%",
      "frequency": "50.0%",
      "leetcodeUrl": "https://leetcode.com/problems/product-of-array-except-self"
    },
    {
      "id": 3024,
      "title": "Type of Triangle",
      "difficulty": "Easy",
      "acceptance": "44.1%",
      "frequency": "62.5%",
      "leetcodeUrl": "https://leetcode.com/problems/type-of-triangle"
    },
    {
      "id": 253,
      "title": "Meeting Rooms II",
      "difficulty": "Medium",
      "acceptance": "52.7%",
      "frequency": "50.0%",
      "leetcodeUrl": "https://leetcode.com/problems/meeting-rooms-ii"
    },
    {
      "id": 1200,
      "title": "Minimum Absolute Difference",
      "difficulty": "Easy",
      "acceptance": "75.1%",
      "frequency": "75.0%",
      "leetcodeUrl": "https://leetcode.com/problems/minimum-absolute-difference"
    },
    {
      "id": 3096,
      "title": "Minimum Levels to Gain More Points",
      "difficulty": "Medium",
      "acceptance": "40.4%",
      "frequency": "62.5%",
      "leetcodeUrl": "https://leetcode.com/problems/minimum-levels-to-gain-more-points"
    },
    {
      "id": 1208,
      "title": "Get Equal Substrings Within Budget",
      "difficulty": "Medium",
      "acceptance": "59.7%",
      "frequency": "37.5%",
      "leetcodeUrl": "https://leetcode.com/problems/get-equal-substrings-within-budget"
    },
    {
      "id": 3147,
      "title": "Taking Maximum Energy From the Mystic Dungeon",
      "difficulty": "Medium",
      "acceptance": "61.0%",
      "frequency": "62.5%",
      "leetcodeUrl": "https://leetcode.com/problems/taking-maximum-energy-from-the-mystic-dungeon"
    },
    {
      "id": 3107,
      "title": "Minimum Operations to Make Median of Array Equal to K",
      "difficulty": "Medium",
      "acceptance": "47.9%",
      "frequency": "75.0%",
      "leetcodeUrl": "https://leetcode.com/problems/minimum-operations-to-make-median-of-array-equal-to-k"
    },
    {
      "id": 3145,
      "title": "Find Products of Elements of Big Array",
      "difficulty": "Hard",
      "acceptance": "24.8%",
      "frequency": "62.5%",
      "leetcodeUrl": "https://leetcode.com/problems/find-products-of-elements-of-big-array"
    },
    {
      "id": 3175,
      "title": "Find The First Player to win K Games in a Row",
      "difficulty": "Medium",
      "acceptance": "40.3%",
      "frequency": "75.0%",
      "leetcodeUrl": "https://leetcode.com/problems/find-the-first-player-to-win-k-games-in-a-row"
    },
    {
      "id": 3159,
      "title": "Find Occurrences of an Element in an Array",
      "difficulty": "Medium",
      "acceptance": "73.4%",
      "frequency": "75.0%",
      "leetcodeUrl": "https://leetcode.com/problems/find-occurrences-of-an-element-in-an-array"
    },
    {
      "id": 412,
      "title": "Fizz Buzz",
      "difficulty": "Easy",
      "acceptance": "75.5%",
      "frequency": "100.0%",
      "leetcodeUrl": "https://leetcode.com/problems/fizz-buzz"
    },
    {
      "id": 443,
      "title": "String Compression",
      "difficulty": "Medium",
      "acceptance": "60.0%",
      "frequency": "50.0%",
      "leetcodeUrl": "https://leetcode.com/problems/string-compression"
    },
    {
      "id": 2432,
      "title": "The Employee That Worked on the Longest Task",
      "difficulty": "Easy",
      "acceptance": "51.7%",
      "frequency": "37.5%",
      "leetcodeUrl": "https://leetcode.com/problems/the-employee-that-worked-on-the-longest-task"
    },
    {
      "id": 1355,
      "title": "Activity Participants",
      "difficulty": "Medium",
      "acceptance": "72.0%",
      "frequency": "75.0%",
      "leetcodeUrl": "https://leetcode.com/problems/activity-participants"
    },
    {
      "id": 1395,
      "title": "Count Number of Teams",
      "difficulty": "Medium",
      "acceptance": "70.2%",
      "frequency": "37.5%",
      "leetcodeUrl": "https://leetcode.com/problems/count-number-of-teams"
    },
    {
      "id": 2455,
      "title": "Average Value of Even Numbers That Are Divisible by Three",
      "difficulty": "Easy",
      "acceptance": "63.2%",
      "frequency": "62.5%",
      "leetcodeUrl": "https://leetcode.com/problems/average-value-of-even-numbers-that-are-divisible-by-three"
    },
    {
      "id": 2545,
      "title": "Sort the Students by Their Kth Score",
      "difficulty": "Medium",
      "acceptance": "86.0%",
      "frequency": "62.5%",
      "leetcodeUrl": "https://leetcode.com/problems/sort-the-students-by-their-kth-score"
    },
    {
      "id": 2598,
      "title": "Smallest Missing Non-negative Integer After Operations",
      "difficulty": "Medium",
      "acceptance": "56.0%",
      "frequency": "37.5%",
      "leetcodeUrl": "https://leetcode.com/problems/smallest-missing-non-negative-integer-after-operations"
    },
    {
      "id": 636,
      "title": "Exclusive Time of Functions",
      "difficulty": "Medium",
      "acceptance": "66.2%",
      "frequency": "50.0%",
      "leetcodeUrl": "https://leetcode.com/problems/exclusive-time-of-functions"
    },
    {
      "id": 2562,
      "title": "Find the Array Concatenation Value",
      "difficulty": "Easy",
      "acceptance": "72.0%",
      "frequency": "62.5%",
      "leetcodeUrl": "https://leetcode.com/problems/find-the-array-concatenation-value"
    },
    {
      "id": 1710,
      "title": "Maximum Units on a Truck",
      "difficulty": "Easy",
      "acceptance": "74.9%",
      "frequency": "62.5%",
      "leetcodeUrl": "https://leetcode.com/problems/maximum-units-on-a-truck"
    },
    {
      "id": 1834,
      "title": "Single-Threaded CPU",
      "difficulty": "Medium",
      "acceptance": "47.7%",
      "frequency": "37.5%",
      "leetcodeUrl": "https://leetcode.com/problems/single-threaded-cpu"
    },
    {
      "id": 3223,
      "title": "Minimum Length of String After Operations",
      "difficulty": "Medium",
      "acceptance": "75.1%",
      "frequency": "62.5%",
      "leetcodeUrl": "https://leetcode.com/problems/minimum-length-of-string-after-operations"
    },
    {
      "id": 696,
      "title": "Count Binary Substrings",
      "difficulty": "Easy",
      "acceptance": "70.4%",
      "frequency": "62.5%",
      "leetcodeUrl": "https://leetcode.com/problems/count-binary-substrings"
    },
    {
      "id": 2972,
      "title": "Count the Number of Incremovable Subarrays II",
      "difficulty": "Hard",
      "acceptance": "40.2%",
      "frequency": "62.5%",
      "leetcodeUrl": "https://leetcode.com/problems/count-the-number-of-incremovable-subarrays-ii"
    },
    {
      "id": 98,
      "title": "Validate Binary Search Tree",
      "difficulty": "Medium",
      "acceptance": "35.8%",
      "frequency": "50.0%",
      "leetcodeUrl": "https://leetcode.com/problems/validate-binary-search-tree"
    },
    {
      "id": 2580,
      "title": "Count Ways to Group Overlapping Ranges",
      "difficulty": "Medium",
      "acceptance": "39.1%",
      "frequency": "87.5%",
      "leetcodeUrl": "https://leetcode.com/problems/count-ways-to-group-overlapping-ranges"
    },
    {
      "id": 1319,
      "title": "Number of Operations to Make Network Connected",
      "difficulty": "Medium",
      "acceptance": "66.5%",
      "frequency": "62.5%",
      "leetcodeUrl": "https://leetcode.com/problems/number-of-operations-to-make-network-connected"
    },
    {
      "id": 560,
      "title": "Subarray Sum Equals K",
      "difficulty": "Medium",
      "acceptance": "47.3%",
      "frequency": "75.0%",
      "leetcodeUrl": "https://leetcode.com/problems/subarray-sum-equals-k"
    },
    {
      "id": 78,
      "title": "Subsets",
      "difficulty": "Medium",
      "acceptance": "82.3%",
      "frequency": "37.5%",
      "leetcodeUrl": "https://leetcode.com/problems/subsets"
    },
    {
      "id": 2559,
      "title": "Count Vowel Strings in Ranges",
      "difficulty": "Medium",
      "acceptance": "67.8%",
      "frequency": "62.5%",
      "leetcodeUrl": "https://leetcode.com/problems/count-vowel-strings-in-ranges"
    },
    {
      "id": 70,
      "title": "Climbing Stairs",
      "difficulty": "Easy",
      "acceptance": "54.1%",
      "frequency": "50.0%",
      "leetcodeUrl": "https://leetcode.com/problems/climbing-stairs"
    },
    {
      "id": 2734,
      "title": "Lexicographically Smallest String After Substring Operation",
      "difficulty": "Medium",
      "acceptance": "34.9%",
      "frequency": "62.5%",
      "leetcodeUrl": "https://leetcode.com/problems/lexicographically-smallest-string-after-substring-operation"
    },
    {
      "id": 844,
      "title": "Backspace String Compare",
      "difficulty": "Easy",
      "acceptance": "49.9%",
      "frequency": "50.0%",
      "leetcodeUrl": "https://leetcode.com/problems/backspace-string-compare"
    },
    {
      "id": 2461,
      "title": "Maximum Sum of Distinct Subarrays With Length K",
      "difficulty": "Medium",
      "acceptance": "43.0%",
      "frequency": "62.5%",
      "leetcodeUrl": "https://leetcode.com/problems/maximum-sum-of-distinct-subarrays-with-length-k"
    },
    {
      "id": 153,
      "title": "Find Minimum in Rotated Sorted Array",
      "difficulty": "Medium",
      "acceptance": "54.7%",
      "frequency": "37.5%",
      "leetcodeUrl": "https://leetcode.com/problems/find-minimum-in-rotated-sorted-array"
    },
    {
      "id": 2602,
      "title": "Minimum Operations to Make All Array Elements Equal",
      "difficulty": "Medium",
      "acceptance": "38.4%",
      "frequency": "75.0%",
      "leetcodeUrl": "https://leetcode.com/problems/minimum-operations-to-make-all-array-elements-equal"
    },
    {
      "id": 54,
      "title": "Spiral Matrix",
      "difficulty": "Medium",
      "acceptance": "56.8%",
      "frequency": "50.0%",
      "leetcodeUrl": "https://leetcode.com/problems/spiral-matrix"
    },
    {
      "id": 832,
      "title": "Flipping an Image",
      "difficulty": "Easy",
      "acceptance": "83.7%",
      "frequency": "37.5%",
      "leetcodeUrl": "https://leetcode.com/problems/flipping-an-image"
    },
    {
      "id": 2950,
      "title": "Number of Divisible Substrings",
      "difficulty": "Medium",
      "acceptance": "74.6%",
      "frequency": "50.0%",
      "leetcodeUrl": "https://leetcode.com/problems/number-of-divisible-substrings"
    },
    {
      "id": 51,
      "title": "N-Queens",
      "difficulty": "Hard",
      "acceptance": "75.5%",
      "frequency": "37.5%",
      "leetcodeUrl": "https://leetcode.com/problems/n-queens"
    },
    {
      "id": 926,
      "title": "Flip String to Monotone Increasing",
      "difficulty": "Medium",
      "acceptance": "61.9%",
      "frequency": "37.5%",
      "leetcodeUrl": "https://leetcode.com/problems/flip-string-to-monotone-increasing"
    },
    {
      "id": 2587,
      "title": "Rearrange Array to Maximize Prefix Score",
      "difficulty": "Medium",
      "acceptance": "42.8%",
      "frequency": "37.5%",
      "leetcodeUrl": "https://leetcode.com/problems/rearrange-array-to-maximize-prefix-score"
    },
    {
      "id": 1888,
      "title": "Minimum Number of Flips to Make the Binary String Alternating",
      "difficulty": "Medium",
      "acceptance": "53.5%",
      "frequency": "62.5%",
      "leetcodeUrl": "https://leetcode.com/problems/minimum-number-of-flips-to-make-the-binary-string-alternating"
    },
    {
      "id": 2134,
      "title": "Minimum Swaps to Group All 1's Together II",
      "difficulty": "Medium",
      "acceptance": "65.6%",
      "frequency": "37.5%",
      "leetcodeUrl": "https://leetcode.com/problems/minimum-swaps-to-group-all-1s-together-ii"
    },
    {
      "id": 56,
      "title": "Merge Intervals",
      "difficulty": "Medium",
      "acceptance": "51.8%",
      "frequency": "87.5%",
      "leetcodeUrl": "https://leetcode.com/problems/merge-intervals"
    },
    {
      "id": 3130,
      "title": "Find All Possible Stable Binary Arrays II",
      "difficulty": "Hard",
      "acceptance": "58.9%",
      "frequency": "37.5%",
      "leetcodeUrl": "https://leetcode.com/problems/find-all-possible-stable-binary-arrays-ii"
    },
    {
      "id": 2506,
      "title": "Count Pairs Of Similar Strings",
      "difficulty": "Easy",
      "acceptance": "73.7%",
      "frequency": "50.0%",
      "leetcodeUrl": "https://leetcode.com/problems/count-pairs-of-similar-strings"
    },
    {
      "id": 2451,
      "title": "Odd String Difference",
      "difficulty": "Easy",
      "acceptance": "62.0%",
      "frequency": "37.5%",
      "leetcodeUrl": "https://leetcode.com/problems/odd-string-difference"
    },
    {
      "id": 2390,
      "title": "Removing Stars From a String",
      "difficulty": "Medium",
      "acceptance": "79.3%",
      "frequency": "37.5%",
      "leetcodeUrl": "https://leetcode.com/problems/removing-stars-from-a-string"
    },
    {
      "id": 2696,
      "title": "Minimum String Length After Removing Substrings",
      "difficulty": "Easy",
      "acceptance": "77.2%",
      "frequency": "50.0%",
      "leetcodeUrl": "https://leetcode.com/problems/minimum-string-length-after-removing-substrings"
    },
    {
      "id": 2406,
      "title": "Divide Intervals Into Minimum Number of Groups",
      "difficulty": "Medium",
      "acceptance": "63.6%",
      "frequency": "37.5%",
      "leetcodeUrl": "https://leetcode.com/problems/divide-intervals-into-minimum-number-of-groups"
    },
    {
      "id": 242,
      "title": "Valid Anagram",
      "difficulty": "Easy",
      "acceptance": "68.1%",
      "frequency": "62.5%",
      "leetcodeUrl": "https://leetcode.com/problems/valid-anagram"
    },
    {
      "id": 15,
      "title": "3Sum",
      "difficulty": "Medium",
      "acceptance": "39.1%",
      "frequency": "62.5%",
      "leetcodeUrl": "https://leetcode.com/problems/3sum"
    },
    {
      "id": 453,
      "title": "Minimum Moves to Equal Array Elements",
      "difficulty": "Medium",
      "acceptance": "58.7%",
      "frequency": "75.0%",
      "leetcodeUrl": "https://leetcode.com/problems/minimum-moves-to-equal-array-elements"
    },
    {
      "id": 268,
      "title": "Missing Number",
      "difficulty": "Easy",
      "acceptance": "72.0%",
      "frequency": "37.5%",
      "leetcodeUrl": "https://leetcode.com/problems/missing-number"
    },
    {
      "id": 1974,
      "title": "Minimum Time to Type Word Using Special Typewriter",
      "difficulty": "Easy",
      "acceptance": "78.7%",
      "frequency": "37.5%",
      "leetcodeUrl": "https://leetcode.com/problems/minimum-time-to-type-word-using-special-typewriter"
    },
    {
      "id": 2038,
      "title": "Remove Colored Pieces if Both Neighbors are the Same Color",
      "difficulty": "Medium",
      "acceptance": "63.1%",
      "frequency": "37.5%",
      "leetcodeUrl": "https://leetcode.com/problems/remove-colored-pieces-if-both-neighbors-are-the-same-color"
    },
    {
      "id": 259,
      "title": "3Sum Smaller",
      "difficulty": "Medium",
      "acceptance": "51.4%",
      "frequency": "37.5%",
      "leetcodeUrl": "https://leetcode.com/problems/3sum-smaller"
    },
    {
      "id": 3295,
      "title": "Report Spam Message",
      "difficulty": "Medium",
      "acceptance": "48.7%",
      "frequency": "50.0%",
      "leetcodeUrl": "https://leetcode.com/problems/report-spam-message"
    },
    {
      "id": 1910,
      "title": "Remove All Occurrences of a Substring",
      "difficulty": "Medium",
      "acceptance": "78.5%",
      "frequency": "37.5%",
      "leetcodeUrl": "https://leetcode.com/problems/remove-all-occurrences-of-a-substring"
    },
    {
      "id": 3402,
      "title": "Minimum Operations to Make Columns Strictly Increasing",
      "difficulty": "Easy",
      "acceptance": "72.7%",
      "frequency": "62.5%",
      "leetcodeUrl": "https://leetcode.com/problems/minimum-operations-to-make-columns-strictly-increasing"
    },
    {
      "id": 210,
      "title": "Course Schedule II",
      "difficulty": "Medium",
      "acceptance": "55.5%",
      "frequency": "37.5%",
      "leetcodeUrl": "https://leetcode.com/problems/course-schedule-ii"
    },
    {
      "id": 767,
      "title": "Reorganize String",
      "difficulty": "Medium",
      "acceptance": "57.1%",
      "frequency": "37.5%",
      "leetcodeUrl": "https://leetcode.com/problems/reorganize-string"
    },
    {
      "id": 2231,
      "title": "Largest Number After Digit Swaps by Parity",
      "difficulty": "Easy",
      "acceptance": "65.4%",
      "frequency": "50.0%",
      "leetcodeUrl": "https://leetcode.com/problems/largest-number-after-digit-swaps-by-parity"
    },
    {
      "id": 1768,
      "title": "Merge Strings Alternately",
      "difficulty": "Easy",
      "acceptance": "82.1%",
      "frequency": "50.0%",
      "leetcodeUrl": "https://leetcode.com/problems/merge-strings-alternately"
    },
    {
      "id": 2948,
      "title": "Make Lexicographically Smallest Array by Swapping Elements",
      "difficulty": "Medium",
      "acceptance": "60.3%",
      "frequency": "37.5%",
      "leetcodeUrl": "https://leetcode.com/problems/make-lexicographically-smallest-array-by-swapping-elements"
    },
    {
      "id": 200,
      "title": "Number of Islands",
      "difficulty": "Medium",
      "acceptance": "64.4%",
      "frequency": "37.5%",
      "leetcodeUrl": "https://leetcode.com/problems/number-of-islands"
    },
    {
      "id": 724,
      "title": "Find Pivot Index",
      "difficulty": "Easy",
      "acceptance": "62.7%",
      "frequency": "62.5%",
      "leetcodeUrl": "https://leetcode.com/problems/find-pivot-index"
    },
    {
      "id": 1752,
      "title": "Check if Array Is Sorted and Rotated",
      "difficulty": "Easy",
      "acceptance": "57.3%",
      "frequency": "37.5%",
      "leetcodeUrl": "https://leetcode.com/problems/check-if-array-is-sorted-and-rotated"
    },
    {
      "id": 1539,
      "title": "Kth Missing Positive Number",
      "difficulty": "Easy",
      "acceptance": "63.5%",
      "frequency": "37.5%",
      "leetcodeUrl": "https://leetcode.com/problems/kth-missing-positive-number"
    },
    {
      "id": 7,
      "title": "Reverse Integer",
      "difficulty": "Medium",
      "acceptance": "31.9%",
      "frequency": "37.5%",
      "leetcodeUrl": "https://leetcode.com/problems/reverse-integer"
    },
    {
      "id": 1051,
      "title": "Height Checker",
      "difficulty": "Easy",
      "acceptance": "81.7%",
      "frequency": "50.0%",
      "leetcodeUrl": "https://leetcode.com/problems/height-checker"
    },
    {
      "id": 206,
      "title": "Reverse Linked List",
      "difficulty": "Easy",
      "acceptance": "80.6%",
      "frequency": "37.5%",
      "leetcodeUrl": "https://leetcode.com/problems/reverse-linked-list"
    },
    {
      "id": 451,
      "title": "Sort Characters By Frequency",
      "difficulty": "Medium",
      "acceptance": "75.3%",
      "frequency": "37.5%",
      "leetcodeUrl": "https://leetcode.com/problems/sort-characters-by-frequency"
    },
    {
      "id": 1413,
      "title": "Minimum Value to Get Positive Step by Step Sum",
      "difficulty": "Easy",
      "acceptance": "64.7%",
      "frequency": "37.5%",
      "leetcodeUrl": "https://leetcode.com/problems/minimum-value-to-get-positive-step-by-step-sum"
    },
    {
      "id": 217,
      "title": "Contains Duplicate",
      "difficulty": "Easy",
      "acceptance": "64.4%",
      "frequency": "37.5%",
      "leetcodeUrl": "https://leetcode.com/problems/contains-duplicate"
    },
    {
      "id": 845,
      "title": "Longest Mountain in Array",
      "difficulty": "Medium",
      "acceptance": "42.1%",
      "frequency": "62.5%",
      "leetcodeUrl": "https://leetcode.com/problems/longest-mountain-in-array"
    },
    {
      "id": 89,
      "title": "Gray Code",
      "difficulty": "Medium",
      "acceptance": "64.9%",
      "frequency": "37.5%",
      "leetcodeUrl": "https://leetcode.com/problems/gray-code"
    },
    {
      "id": 76,
      "title": "Minimum Window Substring",
      "difficulty": "Hard",
      "acceptance": "47.5%",
      "frequency": "50.0%",
      "leetcodeUrl": "https://leetcode.com/problems/minimum-window-substring"
    },
    {
      "id": 151,
      "title": "Reverse Words in a String",
      "difficulty": "Medium",
      "acceptance": "56.4%",
      "frequency": "37.5%",
      "leetcodeUrl": "https://leetcode.com/problems/reverse-words-in-a-string"
    },
    {
      "id": 66,
      "title": "Plus One",
      "difficulty": "Easy",
      "acceptance": "50.0%",
      "frequency": "37.5%",
      "leetcodeUrl": "https://leetcode.com/problems/plus-one"
    },
    {
      "id": 1283,
      "title": "Find the Smallest Divisor Given a Threshold",
      "difficulty": "Medium",
      "acceptance": "65.9%",
      "frequency": "50.0%",
      "leetcodeUrl": "https://leetcode.com/problems/find-the-smallest-divisor-given-a-threshold"
    },
    {
      "id": 67,
      "title": "Add Binary",
      "difficulty": "Easy",
      "acceptance": "58.1%",
      "frequency": "37.5%",
      "leetcodeUrl": "https://leetcode.com/problems/add-binary"
    },
    {
      "id": 135,
      "title": "Candy",
      "difficulty": "Hard",
      "acceptance": "48.5%",
      "frequency": "37.5%",
      "leetcodeUrl": "https://leetcode.com/problems/candy"
    },
    {
      "id": 1004,
      "title": "Max Consecutive Ones III",
      "difficulty": "Medium",
      "acceptance": "67.7%",
      "frequency": "62.5%",
      "leetcodeUrl": "https://leetcode.com/problems/max-consecutive-ones-iii"
    },
    {
      "id": 901,
      "title": "Online Stock Span",
      "difficulty": "Medium",
      "acceptance": "69.1%",
      "frequency": "37.5%",
      "leetcodeUrl": "https://leetcode.com/problems/online-stock-span"
    },
    {
      "id": 33,
      "title": "Search in Rotated Sorted Array",
      "difficulty": "Medium",
      "acceptance": "44.9%",
      "frequency": "37.5%",
      "leetcodeUrl": "https://leetcode.com/problems/search-in-rotated-sorted-array"
    },
    {
      "id": 11,
      "title": "Container With Most Water",
      "difficulty": "Medium",
      "acceptance": "60.0%",
      "frequency": "50.0%",
      "leetcodeUrl": "https://leetcode.com/problems/container-with-most-water"
    },
    {
      "id": 283,
      "title": "Move Zeroes",
      "difficulty": "Easy",
      "acceptance": "63.8%",
      "frequency": "50.0%",
      "leetcodeUrl": "https://leetcode.com/problems/move-zeroes"
    },
    {
      "id": 141,
      "title": "Linked List Cycle",
      "difficulty": "Easy",
      "acceptance": "54.3%",
      "frequency": "37.5%",
      "leetcodeUrl": "https://leetcode.com/problems/linked-list-cycle"
    },
    {
      "id": 350,
      "title": "Intersection of Two Arrays II",
      "difficulty": "Easy",
      "acceptance": "59.9%",
      "frequency": "37.5%",
      "leetcodeUrl": "https://leetcode.com/problems/intersection-of-two-arrays-ii"
    },
    {
      "id": 79,
      "title": "Word Search",
      "difficulty": "Medium",
      "acceptance": "47.4%",
      "frequency": "37.5%",
      "leetcodeUrl": "https://leetcode.com/problems/word-search"
    },
    {
      "id": 1963,
      "title": "Minimum Number of Swaps to Make the String Balanced",
      "difficulty": "Medium",
      "acceptance": "78.0%",
      "frequency": "37.5%",
      "leetcodeUrl": "https://leetcode.com/problems/minimum-number-of-swaps-to-make-the-string-balanced"
    },
    {
      "id": 1163,
      "title": "Last Substring in Lexicographical Order",
      "difficulty": "Hard",
      "acceptance": "35.0%",
      "frequency": "37.5%",
      "leetcodeUrl": "https://leetcode.com/problems/last-substring-in-lexicographical-order"
    },
    {
      "id": 921,
      "title": "Minimum Add to Make Parentheses Valid",
      "difficulty": "Medium",
      "acceptance": "74.4%",
      "frequency": "37.5%",
      "leetcodeUrl": "https://leetcode.com/problems/minimum-add-to-make-parentheses-valid"
    },
    {
      "id": 35,
      "title": "Search Insert Position",
      "difficulty": "Easy",
      "acceptance": "51.3%",
      "frequency": "37.5%",
      "leetcodeUrl": "https://leetcode.com/problems/search-insert-position"
    },
    {
      "id": 45,
      "title": "Jump Game II",
      "difficulty": "Medium",
      "acceptance": "42.9%",
      "frequency": "37.5%",
      "leetcodeUrl": "https://leetcode.com/problems/jump-game-ii"
    },
    {
      "id": 1167,
      "title": "Minimum Cost to Connect Sticks",
      "difficulty": "Medium",
      "acceptance": "71.9%",
      "frequency": "50.0%",
      "leetcodeUrl": "https://leetcode.com/problems/minimum-cost-to-connect-sticks"
    },
    {
      "id": 475,
      "title": "Heaters",
      "difficulty": "Medium",
      "acceptance": "41.9%",
      "frequency": "37.5%",
      "leetcodeUrl": "https://leetcode.com/problems/heaters"
    },
    {
      "id": 1052,
      "title": "Grumpy Bookstore Owner",
      "difficulty": "Medium",
      "acceptance": "64.0%",
      "frequency": "37.5%",
      "leetcodeUrl": "https://leetcode.com/problems/grumpy-bookstore-owner"
    },
    {
      "id": 23,
      "title": "Merge k Sorted Lists",
      "difficulty": "Hard",
      "acceptance": "59.6%",
      "frequency": "37.5%",
      "leetcodeUrl": "https://leetcode.com/problems/merge-k-sorted-lists"
    },
    {
      "id": 1802,
      "title": "Maximum Value at a Given Index in a Bounded Array",
      "difficulty": "Medium",
      "acceptance": "38.9%",
      "frequency": "37.5%",
      "leetcodeUrl": "https://leetcode.com/problems/maximum-value-at-a-given-index-in-a-bounded-array"
    },
    {
      "id": 1604,
      "title": "Alert Using Same Key-Card Three or More Times in a One Hour Period",
      "difficulty": "Medium",
      "acceptance": "46.3%",
      "frequency": "37.5%",
      "leetcodeUrl": "https://leetcode.com/problems/alert-using-same-key-card-three-or-more-times-in-a-one-hour-period"
    },
    {
      "id": 239,
      "title": "Sliding Window Maximum",
      "difficulty": "Hard",
      "acceptance": "48.8%",
      "frequency": "50.0%",
      "leetcodeUrl": "https://leetcode.com/problems/sliding-window-maximum"
    },
    {
      "id": 1518,
      "title": "Water Bottles",
      "difficulty": "Easy",
      "acceptance": "72.6%",
      "frequency": "62.5%",
      "leetcodeUrl": "https://leetcode.com/problems/water-bottles"
    },
    {
      "id": 876,
      "title": "Middle of the Linked List",
      "difficulty": "Easy",
      "acceptance": "81.8%",
      "frequency": "37.5%",
      "leetcodeUrl": "https://leetcode.com/problems/middle-of-the-linked-list"
    },
    {
      "id": 26,
      "title": "Remove Duplicates from Sorted Array",
      "difficulty": "Easy",
      "acceptance": "62.8%",
      "frequency": "37.5%",
      "leetcodeUrl": "https://leetcode.com/problems/remove-duplicates-from-sorted-array"
    },
    {
      "id": 155,
      "title": "Min Stack",
      "difficulty": "Medium",
      "acceptance": "58.2%",
      "frequency": "37.5%",
      "leetcodeUrl": "https://leetcode.com/problems/min-stack"
    },
    {
      "id": 31,
      "title": "Next Permutation",
      "difficulty": "Medium",
      "acceptance": "45.3%",
      "frequency": "37.5%",
      "leetcodeUrl": "https://leetcode.com/problems/next-permutation"
    },
    {
      "id": 735,
      "title": "Asteroid Collision",
      "difficulty": "Medium",
      "acceptance": "47.9%",
      "frequency": "37.5%",
      "leetcodeUrl": "https://leetcode.com/problems/asteroid-collision"
    },
    {
      "id": 2220,
      "title": "Minimum Bit Flips to Convert Number",
      "difficulty": "Easy",
      "acceptance": "87.9%",
      "frequency": "37.5%",
      "leetcodeUrl": "https://leetcode.com/problems/minimum-bit-flips-to-convert-number"
    },
    {
      "id": 754,
      "title": "Reach a Number",
      "difficulty": "Medium",
      "acceptance": "45.1%",
      "frequency": "62.5%",
      "leetcodeUrl": "https://leetcode.com/problems/reach-a-number"
    },
    {
      "id": 994,
      "title": "Rotting Oranges",
      "difficulty": "Medium",
      "acceptance": "58.7%",
      "frequency": "37.5%",
      "leetcodeUrl": "https://leetcode.com/problems/rotting-oranges"
    },
    {
      "id": 435,
      "title": "Non-overlapping Intervals",
      "difficulty": "Medium",
      "acceptance": "57.1%",
      "frequency": "50.0%",
      "leetcodeUrl": "https://leetcode.com/problems/non-overlapping-intervals"
    },
    {
      "id": 322,
      "title": "Coin Change",
      "difficulty": "Medium",
      "acceptance": "48.4%",
      "frequency": "37.5%",
      "leetcodeUrl": "https://leetcode.com/problems/coin-change"
    },
    {
      "id": 1046,
      "title": "Last Stone Weight",
      "difficulty": "Easy",
      "acceptance": "66.5%",
      "frequency": "37.5%",
      "leetcodeUrl": "https://leetcode.com/problems/last-stone-weight"
    },
    {
      "id": 2405,
      "title": "Optimal Partition of String",
      "difficulty": "Medium",
      "acceptance": "78.4%",
      "frequency": "37.5%",
      "leetcodeUrl": "https://leetcode.com/problems/optimal-partition-of-string"
    },
    {
      "id": 71,
      "title": "Simplify Path",
      "difficulty": "Medium",
      "acceptance": "50.6%",
      "frequency": "37.5%",
      "leetcodeUrl": "https://leetcode.com/problems/simplify-path"
    },
    {
      "id": 680,
      "title": "Valid Palindrome II",
      "difficulty": "Easy",
      "acceptance": "44.3%",
      "frequency": "50.0%",
      "leetcodeUrl": "https://leetcode.com/problems/valid-palindrome-ii"
    },
    {
      "id": 3627,
      "title": "Maximum Median Sum of Subsequences of Size 3",
      "difficulty": "Medium",
      "acceptance": "65.1%",
      "frequency": "50.0%",
      "leetcodeUrl": "https://leetcode.com/problems/maximum-median-sum-of-subsequences-of-size-3"
    },
    {
      "id": 2193,
      "title": "Minimum Number of Moves to Make Palindrome",
      "difficulty": "Hard",
      "acceptance": "52.8%",
      "frequency": "37.5%",
      "leetcodeUrl": "https://leetcode.com/problems/minimum-number-of-moves-to-make-palindrome"
    },
    {
      "id": 881,
      "title": "Boats to Save People",
      "difficulty": "Medium",
      "acceptance": "61.8%",
      "frequency": "50.0%",
      "leetcodeUrl": "https://leetcode.com/problems/boats-to-save-people"
    },
    {
      "id": 1526,
      "title": "Minimum Number of Increments on Subarrays to Form a Target Array",
      "difficulty": "Hard",
      "acceptance": "78.2%",
      "frequency": "50.0%",
      "leetcodeUrl": "https://leetcode.com/problems/minimum-number-of-increments-on-subarrays-to-form-a-target-array"
    },
    {
      "id": 1685,
      "title": "Sum of Absolute Differences in a Sorted Array",
      "difficulty": "Medium",
      "acceptance": "68.4%",
      "frequency": "37.5%",
      "leetcodeUrl": "https://leetcode.com/problems/sum-of-absolute-differences-in-a-sorted-array"
    },
    {
      "id": 1513,
      "title": "Number of Substrings With Only 1s",
      "difficulty": "Medium",
      "acceptance": "57.4%",
      "frequency": "37.5%",
      "leetcodeUrl": "https://leetcode.com/problems/number-of-substrings-with-only-1s"
    },
    {
      "id": 387,
      "title": "First Unique Character in a String",
      "difficulty": "Easy",
      "acceptance": "65.5%",
      "frequency": "37.5%",
      "leetcodeUrl": "https://leetcode.com/problems/first-unique-character-in-a-string"
    },
    {
      "id": 1877,
      "title": "Minimize Maximum Pair Sum in Array",
      "difficulty": "Medium",
      "acceptance": "83.3%",
      "frequency": "37.5%",
      "leetcodeUrl": "https://leetcode.com/problems/minimize-maximum-pair-sum-in-array"
    },
    {
      "id": 2,
      "title": "Add Two Numbers",
      "difficulty": "Medium",
      "acceptance": "48.5%",
      "frequency": "37.5%",
      "leetcodeUrl": "https://leetcode.com/problems/add-two-numbers"
    },
    {
      "id": 2273,
      "title": "Find Resultant Array After Removing Anagrams",
      "difficulty": "Easy",
      "acceptance": "69.9%",
      "frequency": "37.5%",
      "leetcodeUrl": "https://leetcode.com/problems/find-resultant-array-after-removing-anagrams"
    },
    {
      "id": 42,
      "title": "Trapping Rain Water",
      "difficulty": "Hard",
      "acceptance": "67.4%",
      "frequency": "37.5%",
      "leetcodeUrl": "https://leetcode.com/problems/trapping-rain-water"
    },
    {
      "id": 32,
      "title": "Longest Valid Parentheses",
      "difficulty": "Hard",
      "acceptance": "38.8%",
      "frequency": "50.0%",
      "leetcodeUrl": "https://leetcode.com/problems/longest-valid-parentheses"
    },
    {
      "id": 1312,
      "title": "Minimum Insertion Steps to Make a String Palindrome",
      "difficulty": "Hard",
      "acceptance": "73.9%",
      "frequency": "37.5%",
      "leetcodeUrl": "https://leetcode.com/problems/minimum-insertion-steps-to-make-a-string-palindrome"
    },
    {
      "id": 763,
      "title": "Partition Labels",
      "difficulty": "Medium",
      "acceptance": "81.9%",
      "frequency": "37.5%",
      "leetcodeUrl": "https://leetcode.com/problems/partition-labels"
    },
    {
      "id": 2429,
      "title": "Minimize XOR",
      "difficulty": "Medium",
      "acceptance": "62.4%",
      "frequency": "37.5%",
      "leetcodeUrl": "https://leetcode.com/problems/minimize-xor"
    },
    {
      "id": 22,
      "title": "Generate Parentheses",
      "difficulty": "Medium",
      "acceptance": "78.7%",
      "frequency": "37.5%",
      "leetcodeUrl": "https://leetcode.com/problems/generate-parentheses"
    },
    {
      "id": 215,
      "title": "Kth Largest Element in an Array",
      "difficulty": "Medium",
      "acceptance": "68.9%",
      "frequency": "37.5%",
      "leetcodeUrl": "https://leetcode.com/problems/kth-largest-element-in-an-array"
    },
    {
      "id": 485,
      "title": "Max Consecutive Ones",
      "difficulty": "Easy",
      "acceptance": "65.2%",
      "frequency": "37.5%",
      "leetcodeUrl": "https://leetcode.com/problems/max-consecutive-ones"
    },
    {
      "id": 875,
      "title": "Koko Eating Bananas",
      "difficulty": "Medium",
      "acceptance": "50.0%",
      "frequency": "37.5%",
      "leetcodeUrl": "https://leetcode.com/problems/koko-eating-bananas"
    },
    {
      "id": 1758,
      "title": "Minimum Changes To Make Alternating Binary String",
      "difficulty": "Easy",
      "acceptance": "67.8%",
      "frequency": "37.5%",
      "leetcodeUrl": "https://leetcode.com/problems/minimum-changes-to-make-alternating-binary-string"
    },
    {
      "id": 3521,
      "title": "Find Product Recommendation Pairs",
      "difficulty": "Medium",
      "acceptance": "61.9%",
      "frequency": "37.5%",
      "leetcodeUrl": "https://leetcode.com/problems/find-product-recommendation-pairs"
    },
    {
      "id": 647,
      "title": "Palindromic Substrings",
      "difficulty": "Medium",
      "acceptance": "72.8%",
      "frequency": "37.5%",
      "leetcodeUrl": "https://leetcode.com/problems/palindromic-substrings"
    },
    {
      "id": 72,
      "title": "Edit Distance",
      "difficulty": "Medium",
      "acceptance": "60.6%",
      "frequency": "37.5%",
      "leetcodeUrl": "https://leetcode.com/problems/edit-distance"
    },
    {
      "id": 371,
      "title": "Sum of Two Integers",
      "difficulty": "Medium",
      "acceptance": "55.5%",
      "frequency": "37.5%",
      "leetcodeUrl": "https://leetcode.com/problems/sum-of-two-integers"
    },
    {
      "id": 992,
      "title": "Subarrays with K Different Integers",
      "difficulty": "Hard",
      "acceptance": "68.1%",
      "frequency": "37.5%",
      "leetcodeUrl": "https://leetcode.com/problems/subarrays-with-k-different-integers"
    },
    {
      "id": 2402,
      "title": "Meeting Rooms III",
      "difficulty": "Hard",
      "acceptance": "51.5%",
      "frequency": "37.5%",
      "leetcodeUrl": "https://leetcode.com/problems/meeting-rooms-iii"
    },
    {
      "id": 75,
      "title": "Sort Colors",
      "difficulty": "Medium",
      "acceptance": "69.6%",
      "frequency": "37.5%",
      "leetcodeUrl": "https://leetcode.com/problems/sort-colors"
    },
    {
      "id": 152,
      "title": "Maximum Product Subarray",
      "difficulty": "Medium",
      "acceptance": "36.4%",
      "frequency": "37.5%",
      "leetcodeUrl": "https://leetcode.com/problems/maximum-product-subarray"
    },
    {
      "id": 1838,
      "title": "Frequency of the Most Frequent Element",
      "difficulty": "Medium",
      "acceptance": "44.8%",
      "frequency": "37.5%",
      "leetcodeUrl": "https://leetcode.com/problems/frequency-of-the-most-frequent-element"
    },
    {
      "id": 191,
      "title": "Number of 1 Bits",
      "difficulty": "Easy",
      "acceptance": "76.8%",
      "frequency": "37.5%",
      "leetcodeUrl": "https://leetcode.com/problems/number-of-1-bits"
    },
    {
      "id": 2116,
      "title": "Check if a Parentheses String Can Be Valid",
      "difficulty": "Medium",
      "acceptance": "45.2%",
      "frequency": "37.5%",
      "leetcodeUrl": "https://leetcode.com/problems/check-if-a-parentheses-string-can-be-valid"
    },
    {
      "id": 202,
      "title": "Happy Number",
      "difficulty": "Easy",
      "acceptance": "59.7%",
      "frequency": "37.5%",
      "leetcodeUrl": "https://leetcode.com/problems/happy-number"
    },
    {
      "id": 347,
      "title": "Top K Frequent Elements",
      "difficulty": "Medium",
      "acceptance": "66.4%",
      "frequency": "37.5%",
      "leetcodeUrl": "https://leetcode.com/problems/top-k-frequent-elements"
    },
    {
      "id": 941,
      "title": "Valid Mountain Array",
      "difficulty": "Easy",
      "acceptance": "35.3%",
      "frequency": "37.5%",
      "leetcodeUrl": "https://leetcode.com/problems/valid-mountain-array"
    }
  ]
}