{
  "company": "Yelp",
  "questions": [
    {
      "id": 1,
      "title": "Two Sum",
      "difficulty": "Easy",
      "acceptance": "57.5%",
      "frequency": "100.0%",
      "leetcodeUrl": "https://leetcode.com/problems/two-sum"
    },
    {
      "id": 3,
      "title": "Longest Substring Without Repeating Characters",
      "difficulty": "Medium",
      "acceptance": "39.1%",
      "frequency": "100.0%",
      "leetcodeUrl": "https://leetcode.com/problems/longest-substring-without-repeating-characters"
    },
    {
      "id": 14,
      "title": "Longest Common Prefix",
      "difficulty": "Easy",
      "acceptance": "47.6%",
      "frequency": "100.0%",
      "leetcodeUrl": "https://leetcode.com/problems/longest-common-prefix"
    },
    {
      "id": 49,
      "title": "Group Anagrams",
      "difficulty": "Medium",
      "acceptance": "72.6%",
      "frequency": "100.0%",
      "leetcodeUrl": "https://leetcode.com/problems/group-anagrams"
    },
    {
      "id": 56,
      "title": "Merge Intervals",
      "difficulty": "Medium",
      "acceptance": "51.8%",
      "frequency": "100.0%",
      "leetcodeUrl": "https://leetcode.com/problems/merge-intervals"
    },
    {
      "id": 126,
      "title": "Word Ladder II",
      "difficulty": "Hard",
      "acceptance": "27.7%",
      "frequency": "100.0%",
      "leetcodeUrl": "https://leetcode.com/problems/word-ladder-ii"
    },
    {
      "id": 127,
      "title": "Word Ladder",
      "difficulty": "Hard",
      "acceptance": "45.6%",
      "frequency": "100.0%",
      "leetcodeUrl": "https://leetcode.com/problems/word-ladder"
    },
    {
      "id": 151,
      "title": "Reverse Words in a String",
      "difficulty": "Medium",
      "acceptance": "56.4%",
      "frequency": "100.0%",
      "leetcodeUrl": "https://leetcode.com/problems/reverse-words-in-a-string"
    },
    {
      "id": 1126,
      "title": "Active Businesses",
      "difficulty": "Medium",
      "acceptance": "66.0%",
      "frequency": "100.0%",
      "leetcodeUrl": "https://leetcode.com/problems/active-businesses"
    },
    {
      "id": 206,
      "title": "Reverse Linked List",
      "difficulty": "Easy",
      "acceptance": "80.6%",
      "frequency": "100.0%",
      "leetcodeUrl": "https://leetcode.com/problems/reverse-linked-list"
    },
    {
      "id": 207,
      "title": "Course Schedule",
      "difficulty": "Medium",
      "acceptance": "51.4%",
      "frequency": "100.0%",
      "leetcodeUrl": "https://leetcode.com/problems/course-schedule"
    },
    {
      "id": 218,
      "title": "The Skyline Problem",
      "difficulty": "Hard",
      "acceptance": "45.4%",
      "frequency": "100.0%",
      "leetcodeUrl": "https://leetcode.com/problems/the-skyline-problem"
    },
    {
      "id": 242,
      "title": "Valid Anagram",
      "difficulty": "Easy",
      "acceptance": "68.1%",
      "frequency": "100.0%",
      "leetcodeUrl": "https://leetcode.com/problems/valid-anagram"
    },
    {
      "id": 347,
      "title": "Top K Frequent Elements",
      "difficulty": "Medium",
      "acceptance": "66.4%",
      "frequency": "100.0%",
      "leetcodeUrl": "https://leetcode.com/problems/top-k-frequent-elements"
    },
    {
      "id": 380,
      "title": "Insert Delete GetRandom O(1)",
      "difficulty": "Medium",
      "acceptance": "55.4%",
      "frequency": "100.0%",
      "leetcodeUrl": "https://leetcode.com/problems/insert-delete-getrandom-o1"
    },
    {
      "id": 381,
      "title": "Insert Delete GetRandom O(1) - Duplicates allowed",
      "difficulty": "Hard",
      "acceptance": "36.6%",
      "frequency": "100.0%",
      "leetcodeUrl": "https://leetcode.com/problems/insert-delete-getrandom-o1-duplicates-allowed"
    },
    {
      "id": 394,
      "title": "Decode String",
      "difficulty": "Medium",
      "acceptance": "62.6%",
      "frequency": "100.0%",
      "leetcodeUrl": "https://leetcode.com/problems/decode-string"
    },
    {
      "id": 1333,
      "title": "Filter Restaurants by Vegan-Friendly, Price and Distance",
      "difficulty": "Medium",
      "acceptance": "64.2%",
      "frequency": "100.0%",
      "leetcodeUrl": "https://leetcode.com/problems/filter-restaurants-by-vegan-friendly-price-and-distance"
    },
    {
      "id": 443,
      "title": "String Compression",
      "difficulty": "Medium",
      "acceptance": "60.0%",
      "frequency": "100.0%",
      "leetcodeUrl": "https://leetcode.com/problems/string-compression"
    },
    {
      "id": 1436,
      "title": "Destination City",
      "difficulty": "Easy",
      "acceptance": "79.5%",
      "frequency": "100.0%",
      "leetcodeUrl": "https://leetcode.com/problems/destination-city"
    },
    {
      "id": 1455,
      "title": "Check If a Word Occurs As a Prefix of Any Word in a Sentence",
      "difficulty": "Easy",
      "acceptance": "68.8%",
      "frequency": "100.0%",
      "leetcodeUrl": "https://leetcode.com/problems/check-if-a-word-occurs-as-a-prefix-of-any-word-in-a-sentence"
    },
    {
      "id": 564,
      "title": "Find the Closest Palindrome",
      "difficulty": "Hard",
      "acceptance": "32.0%",
      "frequency": "100.0%",
      "leetcodeUrl": "https://leetcode.com/problems/find-the-closest-palindrome"
    },
    {
      "id": 599,
      "title": "Minimum Index Sum of Two Lists",
      "difficulty": "Easy",
      "acceptance": "59.9%",
      "frequency": "100.0%",
      "leetcodeUrl": "https://leetcode.com/problems/minimum-index-sum-of-two-lists"
    },
    {
      "id": 692,
      "title": "Top K Frequent Words",
      "difficulty": "Medium",
      "acceptance": "60.2%",
      "frequency": "100.0%",
      "leetcodeUrl": "https://leetcode.com/problems/top-k-frequent-words"
    },
    {
      "id": 784,
      "title": "Letter Case Permutation",
      "difficulty": "Medium",
      "acceptance": "75.8%",
      "frequency": "100.0%",
      "leetcodeUrl": "https://leetcode.com/problems/letter-case-permutation"
    },
    {
      "id": 2904,
      "title": "Shortest and Lexicographically Smallest Beautiful String",
      "difficulty": "Medium",
      "acceptance": "41.1%",
      "frequency": "50.0%",
      "leetcodeUrl": "https://leetcode.com/problems/shortest-and-lexicographically-smallest-beautiful-string"
    },
    {
      "id": 2038,
      "title": "Remove Colored Pieces if Both Neighbors are the Same Color",
      "difficulty": "Medium",
      "acceptance": "63.1%",
      "frequency": "100.0%",
      "leetcodeUrl": "https://leetcode.com/problems/remove-colored-pieces-if-both-neighbors-are-the-same-color"
    }
  ]
}